ntrprtr_fs_forensics/Controller.py
ntrprtr_fs_forensics/__init__.py
ntrprtr_fs_forensics/__main__.py
ntrprtr_fs_forensics/ext/__init__.py
ntrprtr_fs_forensics/ext/ext-group-descriptor-table.json
ntrprtr_fs_forensics/ext/ext-inode.json
ntrprtr_fs_forensics/ext/ext-super-block.json
ntrprtr_fs_forensics/fat/__init__.py
ntrprtr_fs_forensics/fat/fat-directory-entry.json
ntrprtr_fs_forensics/fat/fat-fs-info.json
ntrprtr_fs_forensics/fat/fat-long-filename.json
ntrprtr_fs_forensics/fat/fat-vbr-fat1216.json
ntrprtr_fs_forensics/fat/fat-vbr-fat32.json
ntrprtr_fs_forensics/fat/fat-vbr-type.json
ntrprtr_fs_forensics/fat/fat-vbr.json
ntrprtr_fs_forensics/gpt/__init__.py
ntrprtr_fs_forensics/gpt/gpt-entry.json
ntrprtr_fs_forensics/gpt/gpt-header.json
ntrprtr_fs_forensics/mbr/__init__.py
ntrprtr_fs_forensics/mbr/mbr.json
ntrprtr_fs_forensics/ntfs/__init__.py
ntrprtr_fs_forensics/ntfs/ntfs-attribute-file-name.json
ntrprtr_fs_forensics/ntfs/ntfs-attribute-header-general.json
ntrprtr_fs_forensics/ntfs/ntfs-attribute-header-non-resident.json
ntrprtr_fs_forensics/ntfs/ntfs-attribute-header-resident.json
ntrprtr_fs_forensics/ntfs/ntfs-attribute-standard-information.json
ntrprtr_fs_forensics/ntfs/ntfs-mft-entry-header.json
ntrprtr_fs_forensics/ntfs/ntfs-vbr.json
ntrprtr_fs_forensics-1.0.0.dist-info/LICENSE.md
ntrprtr_fs_forensics-1.0.0.dist-info/METADATA
ntrprtr_fs_forensics-1.0.0.dist-info/WHEEL
ntrprtr_fs_forensics-1.0.0.dist-info/entry_points.txt
ntrprtr_fs_forensics-1.0.0.dist-info/top_level.txt
ntrprtr_fs_forensics-1.0.0.dist-info/RECORD
