Metadata-Version: 2.1
Name: ntrprtr_fs_forensics
Version: 1.0.0
Summary: ntrprtr configurations for forensic analysis of file systems
Home-page: https://github.com/5f0ne/ntrprtr-fs-forensics
Author: 5f0
License: MIT
Classifier: Operating System :: OS Independent 
Classifier: Programming Language :: Python :: 3 
Classifier: License :: OSI Approved :: MIT License 
License-File: LICENSE.md
